odoo/addons/partner_vat_unique/README.rst
odoo/addons/partner_vat_unique/__init__.py
odoo/addons/partner_vat_unique/__manifest__.py
odoo/addons/partner_vat_unique/i18n/de.po
odoo/addons/partner_vat_unique/i18n/es.po
odoo/addons/partner_vat_unique/i18n/fr.po
odoo/addons/partner_vat_unique/i18n/hr.po
odoo/addons/partner_vat_unique/i18n/it.po
odoo/addons/partner_vat_unique/i18n/partner_vat_unique.pot
odoo/addons/partner_vat_unique/i18n/pt.po
odoo/addons/partner_vat_unique/i18n/tr.po
odoo/addons/partner_vat_unique/models/__init__.py
odoo/addons/partner_vat_unique/models/res_config_settings.py
odoo/addons/partner_vat_unique/models/res_partner.py
odoo/addons/partner_vat_unique/readme/CONTRIBUTORS.md
odoo/addons/partner_vat_unique/readme/DESCRIPTION.md
odoo/addons/partner_vat_unique/readme/INSTALL.md
odoo/addons/partner_vat_unique/readme/ROADMAP.md
odoo/addons/partner_vat_unique/static/description/icon.png
odoo/addons/partner_vat_unique/static/description/index.html
odoo/addons/partner_vat_unique/tests/__init__.py
odoo/addons/partner_vat_unique/tests/test_vat_unique.py
odoo/addons/partner_vat_unique/views/res_config_settings_views.xml
odoo_addon_partner_vat_unique-19.0.1.0.0.5.dist-info/METADATA
odoo_addon_partner_vat_unique-19.0.1.0.0.5.dist-info/WHEEL
odoo_addon_partner_vat_unique-19.0.1.0.0.5.dist-info/top_level.txt
odoo_addon_partner_vat_unique-19.0.1.0.0.5.dist-info/RECORD
