Metadata-Version: 2.1
Name: odoo-addon-partner_vat_unique
Version: 19.0.1.0.0.5
Requires-Dist: odoo==19.0.*
Summary: Module to make the VAT number unique for customers and suppliers.
Home-page: https://github.com/OCA/partner-contact
License: AGPL-3
Author: Grant Thornton S.L.P, Odoo Community Association (OCA)
Author-email: support@odoo-community.org
Classifier: Programming Language :: Python
Classifier: Framework :: Odoo
Classifier: Framework :: Odoo :: 19.0
Classifier: License :: OSI Approved :: GNU Affero General Public License v3
